.DS_Store
tetrationcli/__init__.py
tetrationcli/bootstrap.py
tetrationcli/main.py
tetrationcli/controllers/__init__.py
tetrationcli/controllers/agents.py
tetrationcli/controllers/agents_inventory.py
tetrationcli/controllers/applications.py
tetrationcli/controllers/base.py
tetrationcli/controllers/enforcement.py
tetrationcli/controllers/inventory.py
tetrationcli/controllers/policies.py
tetrationcli/controllers/roles.py
tetrationcli/controllers/scopes.py
tetrationcli/controllers/sensors.py
tetrationcli/controllers/swiches.py
tetrationcli/controllers/tet_controller.py
tetrationcli/controllers/users.py
tetrationcli/controllers/vrfs.py
tetrationcli/core/__init__.py
tetrationcli/core/exc.py
tetrationcli/core/version.py
tetrationcli/ext/__init__.py
tetrationcli/plugins/__init__.py
tetrationcli/templates/__init__.py
tetrationcli/templates/agents_list.jinja2
tetrationcli/templates/applications_details_list.jinja2
tetrationcli/templates/applications_list.jinja2
tetrationcli/templates/command1.jinja2
tetrationcli/templates/enforcement_list.jinja2
tetrationcli/templates/enforcement_stats.jinja2
tetrationcli/templates/inventory_details.jinja2
tetrationcli/templates/inventory_list.jinja2
tetrationcli/templates/policies_list.jinja2
tetrationcli/templates/policy_details.jinja2
tetrationcli/templates/roles_list.jinja2
tetrationcli/templates/scopes_list.jinja2
tetrationcli/templates/scopes_policy_order.jinja2
tetrationcli/templates/sensors_list.jinja2
tetrationcli/templates/switches_list.jinja2
tetrationcli/templates/users_list.jinja2
tetrationcli/templates/vrfs_list.jinja2
tetrationcli-1.0.1.dist-info/LICENSE.md
tetrationcli-1.0.1.dist-info/METADATA
tetrationcli-1.0.1.dist-info/WHEEL
tetrationcli-1.0.1.dist-info/entry_points.txt
tetrationcli-1.0.1.dist-info/top_level.txt
tetrationcli-1.0.1.dist-info/RECORD
