Metadata-Version: 2.1
Name: tetrationcli
Version: 1.0.1
Summary: Getting basic interactions with Tetration via our favourite media, the cli
Home-page: https://github.com/jumolinas/tetrationcli
Author: Julio Molina Soler
Author-email: jmolinas@cisco.com
License: MIT License
Platform: UNKNOWN
